transformers_inference_toolkit/__init__.py
transformers_inference_toolkit/deepspeed_utils.py
transformers_inference_toolkit/enums.py
transformers_inference_toolkit/onnx_utils.py
transformers_inference_toolkit/optimizer.py
transformers_inference_toolkit/predictor.py
transformers_inference_toolkit/transformers_utils.py
transformers_inference_toolkit-0.1.1.dist-info/LICENSE
transformers_inference_toolkit-0.1.1.dist-info/WHEEL
transformers_inference_toolkit-0.1.1.dist-info/METADATA
transformers_inference_toolkit-0.1.1.dist-info/RECORD
