Metadata-Version: 2.1
Name: transformers-inference-toolkit
Version: 0.1.1
Summary: A collection of helper methods to simplify optimization and inference of Huggingface Transformers-based models
Home-page: https://github.com/feratur/transformers-inference-toolkit
License: Apache-2.0
Author: Alexey Burlakov
Author-email: feraturdev@gmail.com
Requires-Python: >=3.7,<3.11
Classifier: License :: OSI Approved :: Apache Software License
Classifier: Programming Language :: Python :: 3
Classifier: Programming Language :: Python :: 3.7
Classifier: Programming Language :: Python :: 3.8
Classifier: Programming Language :: Python :: 3.9
Classifier: Programming Language :: Python :: 3.10
Requires-Dist: accelerate (>=0.14.0,<0.15.0)
Requires-Dist: deepspeed (>=0.7.4,<0.8.0)
Requires-Dist: onnx (>=1.12.0,<2.0.0)
Requires-Dist: onnxruntime-gpu (>=1.13.1,<2.0.0)
Requires-Dist: torch (>=1.12.1,<2.0.0)
Requires-Dist: transformers (>=4.24.0,<5.0.0)
Project-URL: Repository, https://github.com/feratur/transformers-inference-toolkit
